thtools/core.cpython-37m-i386-linux-gnu.so
thtools/core.pyi
thtools/fasta.py
thtools/__init__.py
thtools/core.pyx
thtools/crt.py
thtools/py.typed
thtools/utils.py
thtools/core.c
thtools/__main__.py
thtools/app/__init__.py
thtools/app/web/index.css
thtools/app/web/manifest.json
thtools/app/web/scroll.js
thtools/app/web/favicon.svg
thtools/app/web/index.js
thtools/app/web/index.html
thtools/miRBase/Oryza sativa.fa
thtools/miRBase/Oryzias latipes.fa
thtools/miRBase/Infectious laryngotracheitis.fa
thtools/miRBase/Brassica napus.fa
thtools/miRBase/Triops cancriformis.fa
thtools/miRBase/Haemonchus contortus.fa
thtools/miRBase/Glottidia pyramidata.fa
thtools/miRBase/Pinus densata.fa
thtools/miRBase/Schistosoma mansoni.fa
thtools/miRBase/Ictalurus punctatus.fa
thtools/miRBase/Tribolium castaneum.fa
thtools/miRBase/Triticum aestivum.fa
thtools/miRBase/Chrysemys picta.fa
thtools/miRBase/Sarcophilus harrisii.fa
thtools/miRBase/Citrus sinensis.fa
thtools/miRBase/Ciona intestinalis.fa
thtools/miRBase/Drosophila virilis.fa
thtools/miRBase/Dinoponera quadriceps.fa
thtools/miRBase/Herpes B.fa
thtools/miRBase/Macropus eugenii.fa
thtools/miRBase/Linum usitatissimum.fa
thtools/miRBase/Simian foamy.fa
thtools/miRBase/Ascaris suum.fa
thtools/miRBase/Herpesvirus of.fa
thtools/miRBase/Phytophthora ramorum.fa
thtools/miRBase/Macaca mulatta.fa
thtools/miRBase/Bovine herpesvirus.fa
thtools/miRBase/Physcomitrella patens.fa
thtools/miRBase/Drosophila mojavensis.fa
thtools/miRBase/Cunninghamia lanceolata.fa
thtools/miRBase/Zea mays.fa
thtools/miRBase/Anopheles gambiae.fa
thtools/miRBase/Otolemur garnettii.fa
thtools/miRBase/Lotus japonicus.fa
thtools/miRBase/Theobroma cacao.fa
thtools/miRBase/Citrus reticulata.fa
thtools/miRBase/Anas platyrhynchos.fa
thtools/miRBase/Manduca sexta.fa
thtools/miRBase/Pygathrix bieti.fa
thtools/miRBase/Mouse gammaherpesvirus.fa
thtools/miRBase/Gossypium raimondii.fa
thtools/miRBase/Rattus norvegicus.fa
thtools-0.3.0.dist-info/WHEEL
thtools-0.3.0.dist-info/top_level.txt
thtools-0.3.0.dist-info/METADATA
thtools-0.3.0.dist-info/RECORD
thtools-0.3.0.dist-info/COPYING
