Metadata-Version: 2.1
Name: thtools
Version: 0.3.0
Summary: A library for the analysis of toehold switch riboregulators created by the iGEM team City of London UK 2021.
Home-page: https://github.com/lkn849/thtools/
Author: Lucas Ng
Author-email: lkn849@gmail.com
License: GPLv3
Platform: any
Classifier: License :: OSI Approved :: GNU General Public License v3 or later (GPLv3+)
Classifier: Operating System :: OS Independent
Classifier: Intended Audience :: Science/Research
Classifier: Natural Language :: English
Classifier: Programming Language :: Python
Classifier: Programming Language :: Python :: 3
Classifier: Programming Language :: Python :: 3 :: Only
Classifier: Programming Language :: Python :: 3.6
Classifier: Programming Language :: Python :: 3.7
Classifier: Programming Language :: Python :: 3.8
Classifier: Programming Language :: Python :: 3.9
Classifier: Programming Language :: Python :: Implementation :: CPython
Classifier: Typing :: Typed
Requires-Python: <4.0,>=3.6
License-File: COPYING
Requires-Dist: eel (~=0.14)
Requires-Dist: pathos (~=0.2)
Requires-Dist: prettytable (~=2.1)
